odoo/addons/mrp_production_date_planned_finished/README.rst
odoo/addons/mrp_production_date_planned_finished/__init__.py
odoo/addons/mrp_production_date_planned_finished/__manifest__.py
odoo/addons/mrp_production_date_planned_finished/i18n/it.po
odoo/addons/mrp_production_date_planned_finished/i18n/mrp_production_date_planned_finished.pot
odoo/addons/mrp_production_date_planned_finished/models/__init__.py
odoo/addons/mrp_production_date_planned_finished/models/mrp_production.py
odoo/addons/mrp_production_date_planned_finished/readme/CONTRIBUTORS.rst
odoo/addons/mrp_production_date_planned_finished/readme/DESCRIPTION.rst
odoo/addons/mrp_production_date_planned_finished/static/description/icon.png
odoo/addons/mrp_production_date_planned_finished/static/description/index.html
odoo/addons/mrp_production_date_planned_finished/tests/__init__.py
odoo/addons/mrp_production_date_planned_finished/tests/test_date_planned_finished.py
odoo/addons/mrp_production_date_planned_finished/views/mrp_production.xml
odoo_addon_mrp_production_date_planned_finished-15.0.1.0.1.dist-info/METADATA
odoo_addon_mrp_production_date_planned_finished-15.0.1.0.1.dist-info/WHEEL
odoo_addon_mrp_production_date_planned_finished-15.0.1.0.1.dist-info/top_level.txt
odoo_addon_mrp_production_date_planned_finished-15.0.1.0.1.dist-info/RECORD
